{"id": 3985950, "name": "tensorflow/datasets", "isFork": false, "commits": 5998, "branches": 154, "defaultBranch": "master", "releases": 31, "contributors": 263, "license": "Apache License 2.0", "watchers": 111, "stargazers": 3999, "forks": 1464, "size": 991324, "createdAt": "2018-09-10T09:27:22", "pushedAt": "2023-09-11T09:54:51", "updatedAt": "2023-09-11T12:15:55", "homepage": "https://www.tensorflow.org/datasets", "mainLanguage": "Python", "totalIssues": 1077, "openIssues": 391, "totalPullRequests": 3976, "openPullRequests": 255, "blankLines": 155918, "codeLines": 2049266, "commentLines": 47095, "metrics": [{"language": "Python", "blankLines": 22819, "codeLines": 102867, "commentLines": 44333}, {"language": "Forth", "blankLines": 1, "codeLines": 14, "commentLines": 0}, {"language": "JSON", "blankLines": 5, "codeLines": 1409282, "commentLines": 0}, {"language": "Jupyter Notebook", "blankLines": 0, "codeLines": 620, "commentLines": 2359}, {"language": "Ruby", "blankLines": 0, "codeLines": 10, "commentLines": 0}, {"language": "TOML", "blankLines": 0, "codeLines": 7, "commentLines": 3}, {"language": "CSV", "blankLines": 3, "codeLines": 9332, "commentLines": 0}, {"language": "Markdown", "blankLines": 132872, "codeLines": 521666, "commentLines": 0}, {"language": "TeX", "blankLines": 6, "codeLines": 1686, "commentLines": 0}, {"language": "Bourne Shell", "blankLines": 25, "codeLines": 74, "commentLines": 33}, {"language": "XML", "blankLines": 6, "codeLines": 1281, "commentLines": 0}, {"language": "YAML", "blankLines": 56, "codeLines": 2034, "commentLines": 51}, {"language": "Protocol Buffers", "blankLines": 120, "codeLines": 374, "commentLines": 313}, {"language": "Perl", "blankLines": 5, "codeLines": 6, "commentLines": 3}, {"language": "C#", "blankLines": 0, "codeLines": 13, "commentLines": 0}], "lastCommit": "2023-09-11T09:54:43", "lastCommitSHA": "6bb45ccd09cbdfa2ec6bb7c8d9c9433ea1e2d0bc", "hasWiki": false, "isArchived": false, "languages": {"Python": 5766913, "Ruby": 25669, "Roff": 22095, "Smalltalk": 20604, "NewLisp": 13940, "JavaScript": 13369, "Shell": 3895, "TeX": 759, "Gherkin": 728, "Perl": 520}, "labels": ["author:kokoro_test_failed", "author:please_resolve_conflict", "author:please_respond", "bug", "cla: no", "cla: yes", "community:is_reviewing", "community:please_review", "contributions welcome", "copybara-import", "dataset request", "dataset:movielens", "documentation", "enhancement", "help", "icebox", "kokoro:in_progress", "kokoro:run", "py3-migration", "question", "tfds:is_reviewing", "tfds:needs_final_approval", "tfds:please_review", "tfds:ready_to_merge", "wontfix"], "topics": ["data", "dataset", "datasets", "jax", "machine-learning", "numpy", "tensorflow"], "status": "patching_successfully", "repo_folder": "projects/tensorflow_datasets"}