{
    "real_time_counting_targeted_object": "not_executed_yet",
    "vehicle_counting": "not_executed_yet",
    "pedestrian_counting": "not_executed_yet",
    "detection_layer": "not_executed_yet",
    "webcam_counting": "not_executed_yet",
    "real_time_counting": "not_executed_yet",
    "single_image_object_counting": "not_executed_yet",
    "smurf_counting": "not_executed_yet",
    "utils": "not_executed_yet",
    "model": "not_executed_yet",
    "backbone": "not_executed_yet",
    "parallel_model": "not_executed_yet",
    "label_map_util": "not_executed_yet",
    "visualization_utils": "not_executed_yet",
    "object_counting_api": "not_executed_yet",
    "generate_tfrecord": "not_executed_yet",
    "evaluator": "not_executed_yet",
    "trainer": "not_executed_yet",
    "trainer_test": "not_executed_yet",
    "train": "not_executed_yet",
    "eval": "not_executed_yet",
    "__init__": "not_executed_yet",
    "annotation_types": "not_executed_yet",
    "pywrap_mlir": "not_executed_yet",
    "proto_exports": "not_executed_yet",
    "tf2": "not_executed_yet",
    "pywrap_sanitizers": "not_executed_yet",
    "pywrap_tensorflow": "not_executed_yet",
    "pywrap_tfe": "not_executed_yet",
    "dlpack": "not_executed_yet",
    "user_ops": "not_executed_yet",
    "gen_user_ops": "not_executed_yet",
    "python_state": "not_executed_yet",
    "autotrackable": "not_executed_yet",
    "resource": "not_executed_yet",
    "asset": "not_executed_yet",
    "base": "not_executed_yet",
    "layer_utils": "not_executed_yet",
    "base_delegate": "not_executed_yet",
    "data_structures": "not_executed_yet",
    "converter": "not_executed_yet",
    "cli_shared": "not_executed_yet",
    "cli_config": "not_executed_yet",
    "debugger_cli_common": "not_executed_yet",
    "offline_analyzer": "not_executed_yet",
    "analyzer_cli": "not_executed_yet",
    "profile_analyzer_cli": "not_executed_yet",
    "ui_factory": "not_executed_yet",
    "base_ui": "not_executed_yet",
    "readline_ui": "not_executed_yet",
    "tensor_format": "not_executed_yet",
    "framework": "not_executed_yet",
    "grpc_wrapper": "not_executed_yet",
    "local_cli_wrapper": "not_executed_yet",
    "dumping_wrapper": "not_executed_yet",
    "hooks": "not_executed_yet",
    "grpc_debug_server": "not_executed_yet",
    "debug_events_writer": "not_executed_yet",
    "dumping_callback": "not_executed_yet",
    "check_numerics_callback": "not_executed_yet",
    "debug_events_reader": "not_executed_yet",
    "session_debug_testlib": "not_executed_yet",
    "grpc_debug_test_server": "not_executed_yet",
    "dumping_callback_test_lib": "not_executed_yet",
    "debug_data": "not_executed_yet",
    "debug_service_pb2_grpc": "not_executed_yet",
    "debug_graphs": "not_executed_yet",
    "grpc_tensorflow_server": "not_executed_yet",
    "source_utils": "not_executed_yet",
    "source_remote": "not_executed_yet",
    "debug_gradients": "not_executed_yet",
    "debug_events_monitors": "not_executed_yet",
    "function_deserialization": "not_executed_yet",
    "constants": "not_executed_yet",
    "utils_impl": "not_executed_yet",
    "revived_types": "not_executed_yet",
    "signature_serialization": "not_executed_yet",
    "signature_def_utils": "not_executed_yet",
    "fingerprinting_utils": "not_executed_yet",
    "save": "not_executed_yet",
    "tag_constants": "not_executed_yet",
    "builder": "not_executed_yet",
    "save_options": "not_executed_yet",
    "load": "not_executed_yet",
    "main_op": "not_executed_yet",
    "fingerprinting": "not_executed_yet",
    "path_helpers": "not_executed_yet",
    "nested_structure_coder": "not_executed_yet",
    "main_op_impl": "not_executed_yet",
    "saved_model": "not_executed_yet",
    "signature_constants": "not_executed_yet",
    "load_options": "not_executed_yet",
    "loader": "not_executed_yet",
    "builder_impl": "not_executed_yet",
    "simple_save": "not_executed_yet",
    "load_v1_in_v2": "not_executed_yet",
    "signature_def_utils_impl": "not_executed_yet",
    "function_serialization": "not_executed_yet",
    "loader_impl": "not_executed_yet",
    "method_name_updater": "not_executed_yet",
    "tracing_utils": "not_executed_yet",
    "export_utils": "not_executed_yet",
    "export_output": "not_executed_yet",
    "mode_keys": "not_executed_yet",
    "registration": "not_executed_yet",
    "tpu_embedding": "not_executed_yet",
    "session_support": "not_executed_yet",
    "tpu_system_metadata": "not_executed_yet",
    "tpu_embedding_v1": "not_executed_yet",
    "tpu_name_util": "not_executed_yet",
    "device_assignment": "not_executed_yet",
    "training_loop": "not_executed_yet",
    "tpu": "not_executed_yet",
    "tpu_embedding_v2": "not_executed_yet",
    "topology": "not_executed_yet",
    "bfloat16": "not_executed_yet",
    "tpu_hardware_feature": "not_executed_yet",
    "api": "not_executed_yet",
    "tpu_strategy_util": "not_executed_yet",
    "feature_column": "not_executed_yet",
    "tpu_sharding": "not_executed_yet",
    "preempted_hook": "not_executed_yet",
    "tpu_feed": "not_executed_yet",
    "tensor_tracer_report": "not_executed_yet",
    "functional": "not_executed_yet",
    "tpu_embedding_v2_utils": "not_executed_yet",
    "async_checkpoint": "not_executed_yet",
    "tpu_embedding_for_serving": "not_executed_yet",
    "tpu_replication": "not_executed_yet",
    "tensor_tracer_pb2": "not_executed_yet",
    "tpu_embedding_base": "not_executed_yet",
    "feature_column_v2": "not_executed_yet",
    "datasets": "not_executed_yet",
    "tpu_embedding_gradient": "not_executed_yet",
    "tensor_tracer_flags": "not_executed_yet",
    "tpu_optimizer": "not_executed_yet",
    "tensor_tracer": "not_executed_yet",
    "tpu_ops": "not_executed_yet",
    "depthwise_conv_op_base": "not_executed_yet",
    "bias_op_base": "not_executed_yet",
    "cudnn_deterministic_base": "not_executed_yet",
    "xent_op_test_base": "not_executed_yet",
    "sparse_xent_op_test_base": "not_executed_yet",
    "util": "not_executed_yet",
    "test_util": "not_executed_yet",
    "jit": "not_executed_yet",
    "xla": "not_executed_yet",
    "xla_sharding": "not_executed_yet",
    "mlir": "not_executed_yet",
    "trt_convert": "not_executed_yet",
    "tf_trt_integration_test_base": "not_executed_yet",
    "test_base": "not_executed_yet",
    "tf_record_test_base": "not_executed_yet",
    "checkpoint_test_base": "not_executed_yet",
    "shard_op": "not_executed_yet",
    "zip_op": "not_executed_yet",
    "from_tensor_slices_op": "not_executed_yet",
    "sample_from_datasets_op": "not_executed_yet",
    "snapshot_op": "not_executed_yet",
    "multi_device_iterator_ops": "not_executed_yet",
    "from_tensors_op": "not_executed_yet",
    "options": "not_executed_yet",
    "range_op": "not_executed_yet",
    "save_op": "not_executed_yet",
    "batch_op": "not_executed_yet",
    "optional_ops": "not_executed_yet",
    "ignore_errors_op": "not_executed_yet",
    "filter_op": "not_executed_yet",
    "shuffle_op": "not_executed_yet",
    "concatenate_op": "not_executed_yet",
    "random_op": "not_executed_yet",
    "window_op": "not_executed_yet",
    "skip_op": "not_executed_yet",
    "iterator_ops": "not_executed_yet",
    "readers": "not_executed_yet",
    "take_while_op": "not_executed_yet",
    "rebatch_op": "not_executed_yet",
    "unbatch_op": "not_executed_yet",
    "prefetch_op": "not_executed_yet",
    "load_op": "not_executed_yet",
    "debug_mode": "not_executed_yet",
    "group_by_window_op": "not_executed_yet",
    "iterator_autograph": "not_executed_yet",
    "counter_op": "not_executed_yet",
    "flat_map_op": "not_executed_yet",
    "take_op": "not_executed_yet",
    "dataset_autograph": "not_executed_yet",
    "dataset_ops": "not_executed_yet",
    "directed_interleave_op": "not_executed_yet",
    "from_sparse_tensor_slices_op": "not_executed_yet",
    "scan_op": "not_executed_yet",
    "sparse_batch_op": "not_executed_yet",
    "repeat_op": "not_executed_yet",
    "padded_batch_op": "not_executed_yet",
    "structured_function": "not_executed_yet",
    "unique_op": "not_executed_yet",
    "from_generator_op": "not_executed_yet",
    "ragged_batch_op": "not_executed_yet",
    "interleave_op": "not_executed_yet",
    "choose_from_datasets_op": "not_executed_yet",
    "map_op": "not_executed_yet",
    "cache_op": "not_executed_yet",
    "structure": "not_executed_yet",
    "sparse": "not_executed_yet",
    "traverse": "not_executed_yet",
    "nest": "not_executed_yet",
    "convert": "not_executed_yet",
    "random_seed": "not_executed_yet",
    "benchmark_base": "not_executed_yet",
    "multi_process_cluster": "not_executed_yet",
    "matching_files": "not_executed_yet",
    "testing": "not_executed_yet",
    "random_access": "not_executed_yet",
    "batching": "not_executed_yet",
    "distributed_save_op": "not_executed_yet",
    "scan_ops": "not_executed_yet",
    "map_defun": "not_executed_yet",
    "resampling": "not_executed_yet",
    "error_ops": "not_executed_yet",
    "shuffle_ops": "not_executed_yet",
    "io": "not_executed_yet",
    "parsing_ops": "not_executed_yet",
    "distribute": "not_executed_yet",
    "interleave_ops": "not_executed_yet",
    "pad_to_cardinality": "not_executed_yet",
    "prefetching_ops": "not_executed_yet",
    "compression_ops": "not_executed_yet",
    "unique": "not_executed_yet",
    "lookup_ops": "not_executed_yet",
    "writers": "not_executed_yet",
    "random_ops": "not_executed_yet",
    "enumerate_ops": "not_executed_yet",
    "snapshot": "not_executed_yet",
    "cardinality": "not_executed_yet",
    "get_single_element": "not_executed_yet",
    "from_list": "not_executed_yet",
    "data_service_ops": "not_executed_yet",
    "counter": "not_executed_yet",
    "take_while_ops": "not_executed_yet",
    "grouping": "not_executed_yet",
    "server_lib": "not_executed_yet",
    "profiler_client": "not_executed_yet",
    "option_builder": "not_executed_yet",
    "model_analyzer": "not_executed_yet",
    "profiler": "not_executed_yet",
    "trace": "not_executed_yet",
    "tfprof_logger": "not_executed_yet",
    "profiler_v2": "not_executed_yet",
    "flops_registry": "not_executed_yet",
    "control_flow": "not_executed_yet",
    "conditional_expressions": "not_executed_yet",
    "directives": "not_executed_yet",
    "functions": "not_executed_yet",
    "asserts": "not_executed_yet",
    "lists": "not_executed_yet",
    "return_statements": "not_executed_yet",
    "call_trees": "not_executed_yet",
    "logical_expressions": "not_executed_yet",
    "variables": "not_executed_yet",
    "continue_statements": "not_executed_yet",
    "slices": "not_executed_yet",
    "break_statements": "not_executed_yet",
    "special_functions": "not_executed_yet",
    "misc": "not_executed_yet",
    "ag_logging": "not_executed_yet",
    "context_managers": "not_executed_yet",
    "tensor_list": "not_executed_yet",
    "tensors": "not_executed_yet",
    "exceptions": "not_executed_yet",
    "logical": "not_executed_yet",
    "py_builtins": "not_executed_yet",
    "conversion": "not_executed_yet",
    "transpiler": "not_executed_yet",
    "qual_names": "not_executed_yet",
    "error_utils": "not_executed_yet",
    "origin_info": "not_executed_yet",
    "transformer": "not_executed_yet",
    "inspect_utils": "not_executed_yet",
    "cfg": "not_executed_yet",
    "templates": "not_executed_yet",
    "ast_util": "not_executed_yet",
    "parser": "not_executed_yet",
    "naming": "not_executed_yet",
    "reaching_fndefs": "not_executed_yet",
    "type_inference": "not_executed_yet",
    "liveness": "not_executed_yet",
    "activity": "not_executed_yet",
    "reaching_definitions": "not_executed_yet",
    "anf": "not_executed_yet",
    "ag_ctx": "not_executed_yet",
    "function_wrappers": "not_executed_yet",
    "config": "not_executed_yet",
    "converter_testing": "not_executed_yet",
    "unsupported_features_checker": "not_executed_yet",
    "tf_optimizer": "not_executed_yet",
    "cluster": "not_executed_yet",
    "item": "not_executed_yet",
    "summary_iterator": "not_executed_yet",
    "summary": "not_executed_yet",
    "plugin_asset": "not_executed_yet",
    "event_file_writer_v2": "not_executed_yet",
    "writer": "not_executed_yet",
    "event_file_writer": "not_executed_yet",
    "writer_cache": "not_executed_yet",
    "core": "not_executed_yet",
    "data": "not_executed_yet",
    "importer": "not_executed_yet",
    "composite_tensor": "not_executed_yet",
    "op_def_library_pybind": "not_executed_yet",
    "ops": "not_executed_yet",
    "op_def_registry": "not_executed_yet",
    "device_spec": "not_executed_yet",
    "none_tensor": "not_executed_yet",
    "python_memory_checker": "not_executed_yet",
    "extension_type": "not_executed_yet",
    "memory_checker": "not_executed_yet",
    "tensor": "not_executed_yet",
    "extension_type_field": "not_executed_yet",
    "graph_io": "not_executed_yet",
    "test_combinations": "not_executed_yet",
    "dtypes": "not_executed_yet",
    "test_ops": "not_executed_yet",
    "constant_op": "not_executed_yet",
    "error_interpolation": "not_executed_yet",
    "versions": "not_executed_yet",
    "meta_graph": "not_executed_yet",
    "graph_util_impl": "not_executed_yet",
    "c_api_util": "not_executed_yet",
    "errors": "not_executed_yet",
    "tensor_conversion": "not_executed_yet",
    "errors_impl": "not_executed_yet",
    "composite_tensor_gradient": "not_executed_yet",
    "strict_mode": "not_executed_yet",
    "tensor_spec": "not_executed_yet",
    "convert_to_constants": "not_executed_yet",
    "byte_swap_tensor": "not_executed_yet",
    "graph_to_function_def": "not_executed_yet",
    "tensor_shape": "not_executed_yet",
    "type_utils": "not_executed_yet",
    "smart_cond": "not_executed_yet",
    "type_spec_registry": "not_executed_yet",
    "kernels": "not_executed_yet",
    "op_callbacks": "not_executed_yet",
    "function": "not_executed_yet",
    "function_def_to_graph": "not_executed_yet",
    "framework_lib": "not_executed_yet",
    "device": "not_executed_yet",
    "stack": "not_executed_yet",
    "op_def_library": "not_executed_yet",
    "auto_control_deps": "not_executed_yet",
    "subscribe": "not_executed_yet",
    "graph_util": "not_executed_yet",
    "auto_control_deps_utils": "not_executed_yet",
    "tensor_util": "not_executed_yet",
    "func_graph": "not_executed_yet",
    "type_spec": "not_executed_yet",
    "cpp_shape_inference_pb2": "not_executed_yet",
    "tensor_conversion_registry": "not_executed_yet",
    "indexed_slices": "not_executed_yet",
    "combinations": "not_executed_yet",
    "common_shapes": "not_executed_yet",
    "load_library": "not_executed_yet",
    "registry": "not_executed_yet",
    "flexible_dtypes": "not_executed_yet",
    "sparse_tensor": "not_executed_yet",
    "compat": "not_executed_yet",
    "v2_compat": "not_executed_yet",
    "layers": "not_executed_yet",
    "normalization": "not_executed_yet",
    "pooling": "not_executed_yet",
    "convolutional": "not_executed_yet",
    "callbacks_v1": "not_executed_yet",
    "optimizers": "not_executed_yet",
    "regularizers": "not_executed_yet",
    "callbacks": "not_executed_yet",
    "backend_config": "not_executed_yet",
    "metrics": "not_executed_yet",
    "keras_parameterized": "not_executed_yet",
    "backend": "not_executed_yet",
    "losses": "not_executed_yet",
    "testing_utils": "not_executed_yet",
    "optimizer_v1": "not_executed_yet",
    "constraints": "not_executed_yet",
    "activations": "not_executed_yet",
    "models": "not_executed_yet",
    "kernelized_utils": "not_executed_yet",
    "version_utils": "not_executed_yet",
    "all_utils": "not_executed_yet",
    "generic_utils": "not_executed_yet",
    "dataset_creator": "not_executed_yet",
    "conv_utils": "not_executed_yet",
    "tf_utils": "not_executed_yet",
    "vis_utils": "not_executed_yet",
    "tf_inspect": "not_executed_yet",
    "control_flow_util": "not_executed_yet",
    "tf_contextlib": "not_executed_yet",
    "data_utils": "not_executed_yet",
    "metrics_utils": "not_executed_yet",
    "losses_utils": "not_executed_yet",
    "variable_scope_shim": "not_executed_yet",
    "convolutional_recurrent": "not_executed_yet",
    "merge": "not_executed_yet",
    "serialization": "not_executed_yet",
    "recurrent": "not_executed_yet",
    "advanced_activations": "not_executed_yet",
    "embeddings": "not_executed_yet",
    "dense_attention": "not_executed_yet",
    "rnn_cell_wrapper_impl": "not_executed_yet",
    "initializers_v2": "not_executed_yet",
    "initializers_v1": "not_executed_yet",
    "worker_training_state": "not_executed_yet",
    "distributed_training_utils_v1": "not_executed_yet",
    "distributed_training_utils": "not_executed_yet",
    "distribute_coordinator_utils": "not_executed_yet",
    "distributed_file_utils": "not_executed_yet",
    "keras_tensor": "not_executed_yet",
    "base_preprocessing_layer": "not_executed_yet",
    "node": "not_executed_yet",
    "base_layer_utils": "not_executed_yet",
    "input_layer": "not_executed_yet",
    "training_eager_v1": "not_executed_yet",
    "input_spec": "not_executed_yet",
    "compile_utils": "not_executed_yet",
    "training_generator_v1": "not_executed_yet",
    "sequential": "not_executed_yet",
    "training": "not_executed_yet",
    "training_v1": "not_executed_yet",
    "training_utils_v1": "not_executed_yet",
    "partial_batch_padding_handler": "not_executed_yet",
    "training_utils": "not_executed_yet",
    "base_layer_v1": "not_executed_yet",
    "base_layer": "not_executed_yet",
    "data_adapter": "not_executed_yet",
    "training_arrays_v1": "not_executed_yet",
    "training_distributed_v1": "not_executed_yet",
    "optimizer_v2": "not_executed_yet",
    "gradient_descent": "not_executed_yet",
    "adagrad": "not_executed_yet",
    "adamax": "not_executed_yet",
    "learning_rate_schedule": "not_executed_yet",
    "rmsprop": "not_executed_yet",
    "adadelta": "not_executed_yet",
    "legacy_learning_rate_decay": "not_executed_yet",
    "ftrl": "not_executed_yet",
    "adam": "not_executed_yet",
    "nadam": "not_executed_yet",
    "saved_metadata_pb2": "not_executed_yet",
    "saving_utils": "not_executed_yet",
    "saved_model_experimental": "not_executed_yet",
    "hdf5_format": "not_executed_yet",
    "model_config": "not_executed_yet",
    "model_serialization": "not_executed_yet",
    "layer_serialization": "not_executed_yet",
    "base_serialization": "not_executed_yet",
    "serialized_attributes": "not_executed_yet",
    "network_serialization": "not_executed_yet",
    "save_impl": "not_executed_yet",
    "json_utils": "not_executed_yet",
    "metric_serialization": "not_executed_yet",
    "loss_scale_optimizer": "not_executed_yet",
    "autocast_variable": "not_executed_yet",
    "loss_scale": "not_executed_yet",
    "policy": "not_executed_yet",
    "device_compatibility_check": "not_executed_yet",
    "get_layer_policy": "not_executed_yet",
    "gen_parsing_ops": "not_executed_yet",
    "gen_math_ops": "not_executed_yet",
    "histogram_ops": "not_executed_yet",
    "while_v2_indexed_slices_rewriter": "not_executed_yet",
    "critical_section_ops": "not_executed_yet",
    "gen_bitwise_ops": "not_executed_yet",
    "gen_random_index_shuffle_ops": "not_executed_yet",
    "partitioned_variables": "not_executed_yet",
    "bitwise_ops": "not_executed_yet",
    "random_crop_ops": "not_executed_yet",
    "gen_stateful_random_ops": "not_executed_yet",
    "control_flow_switch_case": "not_executed_yet",
    "gen_array_ops": "not_executed_yet",
    "template": "not_executed_yet",
    "gradient_checker": "not_executed_yet",
    "gen_cudnn_rnn_ops": "not_executed_yet",
    "script_ops": "not_executed_yet",
    "random_ops_util": "not_executed_yet",
    "clip_ops": "not_executed_yet",
    "init_ops_v2": "not_executed_yet",
    "gen_encode_proto_ops": "not_executed_yet",
    "collective_ops": "not_executed_yet",
    "gen_experimental_dataset_ops": "not_executed_yet",
    "session_ops": "not_executed_yet",
    "nn_ops": "not_executed_yet",
    "sparse_ops": "not_executed_yet",
    "weak_tensor_ops": "not_executed_yet",
    "initializers_ns": "not_executed_yet",
    "image_ops_impl": "not_executed_yet",
    "shape_util": "not_executed_yet",
    "gen_stateless_random_ops": "not_executed_yet",
    "gen_set_ops": "not_executed_yet",
    "weak_tensor_test_util": "not_executed_yet",
    "list_ops": "not_executed_yet",
    "cond": "not_executed_yet",
    "init_ops": "not_executed_yet",
    "autograph_ops": "not_executed_yet",
    "gen_resource_variable_ops": "not_executed_yet",
    "state_ops": "not_executed_yet",
    "summary_ops_v2": "not_executed_yet",
    "gen_checkpoint_ops": "not_executed_yet",
    "weights_broadcast_ops": "not_executed_yet",
    "confusion_matrix": "not_executed_yet",
    "clustering_ops": "not_executed_yet",
    "control_flow_v2_toggles": "not_executed_yet",
    "gen_rnn_ops": "not_executed_yet",
    "io_ops": "not_executed_yet",
    "numerics": "not_executed_yet",
    "inplace_ops": "not_executed_yet",
    "control_flow_util_v2": "not_executed_yet",
    "gen_debug_ops": "not_executed_yet",
    "while_v2": "not_executed_yet",
    "stateless_random_ops": "not_executed_yet",
    "gen_collective_ops": "not_executed_yet",
    "standard_ops": "not_executed_yet",
    "metrics_impl": "not_executed_yet",
    "sparse_grad": "not_executed_yet",
    "math_grad": "not_executed_yet",
    "functional_ops": "not_executed_yet",
    "gen_logging_ops": "not_executed_yet",
    "ref_variable": "not_executed_yet",
    "cond_v2": "not_executed_yet",
    "resource_variable_ops": "not_executed_yet",
    "ctc_ops": "not_executed_yet",
    "gen_list_ops": "not_executed_yet",
    "manip_ops": "not_executed_yet",
    "gen_sdca_ops": "not_executed_yet",
    "data_flow_ops": "not_executed_yet",
    "sets_impl": "not_executed_yet",
    "gen_ctc_ops": "not_executed_yet",
    "gen_random_ops": "not_executed_yet",
    "gen_nccl_ops": "not_executed_yet",
    "gen_summary_ops": "not_executed_yet",
    "cudnn_rnn_grad": "not_executed_yet",
    "nn_grad": "not_executed_yet",
    "array_ops": "not_executed_yet",
    "map_ops": "not_executed_yet",
    "map_fn": "not_executed_yet",
    "gradients": "not_executed_yet",
    "gen_training_ops": "not_executed_yet",
    "gen_nn_ops": "not_executed_yet",
    "custom_gradient": "not_executed_yet",
    "gen_lookup_ops": "not_executed_yet",
    "rnn_cell_impl": "not_executed_yet",
    "gen_stateless_random_ops_v2": "not_executed_yet",
    "gen_optional_ops": "not_executed_yet",
    "gen_decode_proto_ops": "not_executed_yet",
    "linalg_grad": "not_executed_yet",
    "boosted_trees_ops": "not_executed_yet",
    "gen_functional_ops": "not_executed_yet",
    "gen_spectral_ops": "not_executed_yet",
    "manip_grad": "not_executed_yet",
    "proto_ops": "not_executed_yet",
    "rnn_grad": "not_executed_yet",
    "control_flow_assert": "not_executed_yet",
    "gen_linalg_ops": "not_executed_yet",
    "random_grad": "not_executed_yet",
    "gen_sparse_ops": "not_executed_yet",
    "gen_control_flow_ops": "not_executed_yet",
    "candidate_sampling_ops": "not_executed_yet",
    "resources": "not_executed_yet",
    "array_grad": "not_executed_yet",
    "optional_grad": "not_executed_yet",
    "gen_ragged_conversion_ops": "not_executed_yet",
    "control_flow_case": "not_executed_yet",
    "gen_audio_ops": "not_executed_yet",
    "variable_scope": "not_executed_yet",
    "gen_tpu_ops": "not_executed_yet",
    "gen_sendrecv_ops": "not_executed_yet",
    "tensor_array_ops": "not_executed_yet",
    "sdca_ops": "not_executed_yet",
    "gen_dataset_ops": "not_executed_yet",
    "op_selector": "not_executed_yet",
    "linalg_ops_impl": "not_executed_yet",
    "data_flow_grad": "not_executed_yet",
    "stateful_random_ops": "not_executed_yet",
    "control_flow_v2_func_graphs": "not_executed_yet",
    "bincount_ops": "not_executed_yet",
    "gen_image_ops": "not_executed_yet",
    "gen_filesystem_ops": "not_executed_yet",
    "gradient_checker_v2": "not_executed_yet",
    "string_ops": "not_executed_yet",
    "gen_io_ops": "not_executed_yet",
    "nn_impl_distribute": "not_executed_yet",
    "sort_ops": "not_executed_yet",
    "summary_op_util": "not_executed_yet",
    "gen_candidate_sampling_ops": "not_executed_yet",
    "gen_special_math_ops": "not_executed_yet",
    "control_flow_ops": "not_executed_yet",
    "gen_batch_ops": "not_executed_yet",
    "control_flow_grad": "not_executed_yet",
    "gen_manip_ops": "not_executed_yet",
    "gen_string_ops": "not_executed_yet",
    "linalg_ops": "not_executed_yet",
    "control_flow_state": "not_executed_yet",
    "gradients_util": "not_executed_yet",
    "handle_data_util": "not_executed_yet",
    "rnn": "not_executed_yet",
    "gen_map_ops": "not_executed_yet",
    "filesystem_ops": "not_executed_yet",
    "special_math_ops": "not_executed_yet",
    "gen_uniform_quant_ops": "not_executed_yet",
    "math_ops": "not_executed_yet",
    "batch_ops": "not_executed_yet",
    "gen_count_ops": "not_executed_yet",
    "tensor_array_grad": "not_executed_yet",
    "nn_impl": "not_executed_yet",
    "image_grad_test_base": "not_executed_yet",
    "composite_tensor_ops": "not_executed_yet",
    "image_ops": "not_executed_yet",
    "gen_boosted_trees_ops": "not_executed_yet",
    "logging_ops": "not_executed_yet",
    "default_gradient": "not_executed_yet",
    "gen_sync_ops": "not_executed_yet",
    "unconnected_gradients": "not_executed_yet",
    "gen_ragged_math_ops": "not_executed_yet",
    "gen_state_ops": "not_executed_yet",
    "embedding_ops": "not_executed_yet",
    "parsing_config": "not_executed_yet",
    "array_ops_stack": "not_executed_yet",
    "check_ops": "not_executed_yet",
    "nccl_ops": "not_executed_yet",
    "gen_ragged_array_ops": "not_executed_yet",
    "nn": "not_executed_yet",
    "gen_tpu_partition_ops": "not_executed_yet",
    "gradients_impl": "not_executed_yet",
    "while_loop": "not_executed_yet",
    "gen_clustering_ops": "not_executed_yet",
    "variable_v1": "not_executed_yet",
    "gen_script_ops": "not_executed_yet",
    "nn_fused_batch_norm_grad": "not_executed_yet",
    "gen_composite_tensor_ops": "not_executed_yet",
    "gen_data_flow_ops": "not_executed_yet",
    "state_grad": "not_executed_yet",
    "image_grad": "not_executed_yet",
    "row_partition": "not_executed_yet",
    "ragged_check_ops": "not_executed_yet",
    "ragged_factory_ops": "not_executed_yet",
    "ragged_getitem": "not_executed_yet",
    "ragged_functional_ops": "not_executed_yet",
    "ragged_tensor_value": "not_executed_yet",
    "ragged_tensor_test_ops": "not_executed_yet",
    "ragged_batch_gather_ops": "not_executed_yet",
    "ragged_math_ops": "not_executed_yet",
    "ragged_map_ops": "not_executed_yet",
    "ragged_autograph": "not_executed_yet",
    "ragged_tensor_shape": "not_executed_yet",
    "segment_id_ops": "not_executed_yet",
    "ragged_string_ops": "not_executed_yet",
    "ragged_batch_gather_with_default_op": "not_executed_yet",
    "ragged_where_op": "not_executed_yet",
    "ragged_util": "not_executed_yet",
    "ragged_bincount_ops": "not_executed_yet",
    "ragged_tensor": "not_executed_yet",
    "ragged_image_ops": "not_executed_yet",
    "ragged_gather_ops": "not_executed_yet",
    "ragged_array_ops": "not_executed_yet",
    "ragged_ops": "not_executed_yet",
    "ragged_concat_ops": "not_executed_yet",
    "ragged_embedding_ops": "not_executed_yet",
    "ragged_squeeze_op": "not_executed_yet",
    "ragged_dispatch": "not_executed_yet",
    "dynamic_ragged_shape": "not_executed_yet",
    "ragged_operators": "not_executed_yet",
    "ragged_conversion_ops": "not_executed_yet",
    "exponential": "not_executed_yet",
    "distribution": "not_executed_yet",
    "beta": "not_executed_yet",
    "dirichlet": "not_executed_yet",
    "special_math": "not_executed_yet",
    "gamma": "not_executed_yet",
    "bernoulli": "not_executed_yet",
    "laplace": "not_executed_yet",
    "normal": "not_executed_yet",
    "bijector_test_util": "not_executed_yet",
    "identity_bijector": "not_executed_yet",
    "bijector_impl": "not_executed_yet",
    "dirichlet_multinomial": "not_executed_yet",
    "kullback_leibler": "not_executed_yet",
    "multinomial": "not_executed_yet",
    "uniform": "not_executed_yet",
    "bijector": "not_executed_yet",
    "student_t": "not_executed_yet",
    "categorical": "not_executed_yet",
    "distributions": "not_executed_yet",
    "np_config": "not_executed_yet",
    "np_arrays": "not_executed_yet",
    "np_dtypes": "not_executed_yet",
    "np_utils": "not_executed_yet",
    "np_array_ops": "not_executed_yet",
    "np_random": "not_executed_yet",
    "np_math_ops": "not_executed_yet",
    "structured_tensor": "not_executed_yet",
    "structured_ops": "not_executed_yet",
    "structured_tensor_dynamic": "not_executed_yet",
    "structured_array_ops": "not_executed_yet",
    "losses_impl": "not_executed_yet",
    "linear_operator_zeros": "not_executed_yet",
    "linear_operator_circulant": "not_executed_yet",
    "linear_operator": "not_executed_yet",
    "linear_operator_block_lower_triangular": "not_executed_yet",
    "linear_operator_low_rank_update": "not_executed_yet",
    "linear_operator_composition": "not_executed_yet",
    "linear_operator_lower_triangular": "not_executed_yet",
    "linear_operator_kronecker": "not_executed_yet",
    "linear_operator_householder": "not_executed_yet",
    "linear_operator_tridiag": "not_executed_yet",
    "linear_operator_diag": "not_executed_yet",
    "linear_operator_identity": "not_executed_yet",
    "linear_operator_util": "not_executed_yet",
    "linear_operator_addition": "not_executed_yet",
    "linear_operator_test_util": "not_executed_yet",
    "linear_operator_toeplitz": "not_executed_yet",
    "linear_operator_full_matrix": "not_executed_yet",
    "linear_operator_block_diag": "not_executed_yet",
    "linear_operator_adjoint": "not_executed_yet",
    "linear_operator_inversion": "not_executed_yet",
    "slicing": "not_executed_yet",
    "linear_operator_permutation": "not_executed_yet",
    "linalg_impl": "not_executed_yet",
    "gen_sparse_csr_matrix_ops": "not_executed_yet",
    "sparse_csr_matrix_grad": "not_executed_yet",
    "conjugate_gradient": "not_executed_yet",
    "sparse_csr_matrix_ops": "not_executed_yet",
    "pfor": "not_executed_yet",
    "fft_ops": "not_executed_yet",
    "signal": "not_executed_yet",
    "shape_ops": "not_executed_yet",
    "mel_ops": "not_executed_yet",
    "util_ops": "not_executed_yet",
    "spectral_ops": "not_executed_yet",
    "mfcc_ops": "not_executed_yet",
    "dct_ops": "not_executed_yet",
    "reconstruction_ops": "not_executed_yet",
    "window_ops": "not_executed_yet",
    "remote": "not_executed_yet",
    "backprop_util": "not_executed_yet",
    "tape": "not_executed_yet",
    "forwardprop": "not_executed_yet",
    "graph_only_ops": "not_executed_yet",
    "test": "not_executed_yet",
    "executor": "not_executed_yet",
    "backprop": "not_executed_yet",
    "benchmarks_test_base": "not_executed_yet",
    "monitoring": "not_executed_yet",
    "cancellation": "not_executed_yet",
    "execute": "not_executed_yet",
    "def_function": "not_executed_yet",
    "imperative_grad": "not_executed_yet",
    "lift_to_graph": "not_executed_yet",
    "record": "not_executed_yet",
    "context": "not_executed_yet",
    "forwardprop_util": "not_executed_yet",
    "wrap_function": "not_executed_yet",
    "atomic_function": "not_executed_yet",
    "saved_model_utils": "not_executed_yet",
    "eager_function_run": "not_executed_yet",
    "composite_tensor_utils": "not_executed_yet",
    "function_type_utils": "not_executed_yet",
    "concrete_function": "not_executed_yet",
    "tf_method_target": "not_executed_yet",
    "saved_model_exported_concrete": "not_executed_yet",
    "polymorphic_function": "not_executed_yet",
    "compiler_ir": "not_executed_yet",
    "attributes": "not_executed_yet",
    "autograph_util": "not_executed_yet",
    "function_context": "not_executed_yet",
    "tracing_compilation": "not_executed_yet",
    "memory_test_util": "not_executed_yet",
    "session": "not_executed_yet",
    "device_lib": "not_executed_yet",
    "client_lib": "not_executed_yet",
    "timeline": "not_executed_yet",
    "pywrap_tf_session": "not_executed_yet",
    "variable_utils": "not_executed_yet",
    "deprecated_module": "not_executed_yet",
    "keyword_args": "not_executed_yet",
    "tf_stack": "not_executed_yet",
    "nest_util": "not_executed_yet",
    "deprecation": "not_executed_yet",
    "dispatch": "not_executed_yet",
    "all_util": "not_executed_yet",
    "object_identity": "not_executed_yet",
    "module_wrapper": "not_executed_yet",
    "keras_deps": "not_executed_yet",
    "example_parser_configuration": "not_executed_yet",
    "traceback_utils": "not_executed_yet",
    "tf_should_use": "not_executed_yet",
    "tf_export": "not_executed_yet",
    "tf_decorator_export": "not_executed_yet",
    "function_utils": "not_executed_yet",
    "lazy_loader": "not_executed_yet",
    "module": "not_executed_yet",
    "tf_record": "not_executed_yet",
    "file_io": "not_executed_yet",
    "single_loss_example": "not_executed_yet",
    "ps_values": "not_executed_yet",
    "numpy_dataset": "not_executed_yet",
    "estimator_training": "not_executed_yet",
    "mirrored_strategy": "not_executed_yet",
    "input_ops": "not_executed_yet",
    "multi_process_runner": "not_executed_yet",
    "distribute_coordinator": "not_executed_yet",
    "distribute_lib": "not_executed_yet",
    "strategy_combinations": "not_executed_yet",
    "strategy_test_lib": "not_executed_yet",
    "device_util": "not_executed_yet",
    "packed_distributed_variable": "not_executed_yet",
    "tpu_util": "not_executed_yet",
    "reduce_util": "not_executed_yet",
    "tpu_values": "not_executed_yet",
    "input_lib": "not_executed_yet",
    "tpu_replicated_variable": "not_executed_yet",
    "collective_util": "not_executed_yet",
    "central_storage_strategy": "not_executed_yet",
    "step_fn": "not_executed_yet",
    "input_util": "not_executed_yet",
    "mirrored_run": "not_executed_yet",
    "parameter_server_strategy": "not_executed_yet",
    "cross_device_ops": "not_executed_yet",
    "one_device_strategy": "not_executed_yet",
    "values": "not_executed_yet",
    "sharded_variable": "not_executed_yet",
    "multi_worker_test_base": "not_executed_yet",
    "multi_process_lib": "not_executed_yet",
    "distribute_utils": "not_executed_yet",
    "tpu_strategy": "not_executed_yet",
    "values_util": "not_executed_yet",
    "merge_call_interim": "not_executed_yet",
    "values_v2": "not_executed_yet",
    "parameter_server_strategy_v2": "not_executed_yet",
    "collective_all_reduce_strategy": "not_executed_yet",
    "multi_worker_util": "not_executed_yet",
    "cross_device_utils": "not_executed_yet",
    "slurm_cluster_resolver": "not_executed_yet",
    "tfconfig_cluster_resolver": "not_executed_yet",
    "kubernetes_cluster_resolver": "not_executed_yet",
    "tpu_cluster_resolver": "not_executed_yet",
    "cluster_resolver": "not_executed_yet",
    "gce_cluster_resolver": "not_executed_yet",
    "sagemaker_cluster_resolver": "not_executed_yet",
    "preemption_watcher": "not_executed_yet",
    "failure_handling": "not_executed_yet",
    "failure_handling_util": "not_executed_yet",
    "remote_value": "not_executed_yet",
    "metric_utils": "not_executed_yet",
    "fault_tolerance_test_base": "not_executed_yet",
    "cluster_coordinator": "not_executed_yet",
    "coordinator_context": "not_executed_yet",
    "all_reduce": "not_executed_yet",
    "dtensor_strategy_extended": "not_executed_yet",
    "dtensor_util": "not_executed_yet",
    "multi_worker_mirrored_strategy": "not_executed_yet",
    "rpc_ops": "not_executed_yet",
    "parallel_device": "not_executed_yet",
    "checkpoint_ops": "not_executed_yet",
    "basic_session_run_hooks": "not_executed_yet",
    "warm_starting_util": "not_executed_yet",
    "supervisor": "not_executed_yet",
    "device_setter": "not_executed_yet",
    "training_ops": "not_executed_yet",
    "coordinator": "not_executed_yet",
    "proximal_adagrad": "not_executed_yet",
    "summary_io": "not_executed_yet",
    "sync_replicas_optimizer": "not_executed_yet",
    "optimizer": "not_executed_yet",
    "proximal_gradient_descent": "not_executed_yet",
    "momentum": "not_executed_yet",
    "training_util": "not_executed_yet",
    "session_manager": "not_executed_yet",
    "py_checkpoint_reader": "not_executed_yet",
    "adagrad_da": "not_executed_yet",
    "saver": "not_executed_yet",
    "slot_creator": "not_executed_yet",
    "checkpoint_utils": "not_executed_yet",
    "queue_runner_impl": "not_executed_yet",
    "checkpoint_management": "not_executed_yet",
    "saver_test_utils": "not_executed_yet",
    "quantize_training": "not_executed_yet",
    "input": "not_executed_yet",
    "learning_rate_decay": "not_executed_yet",
    "session_run_hook": "not_executed_yet",
    "monitored_session": "not_executed_yet",
    "basic_loops": "not_executed_yet",
    "moving_averages": "not_executed_yet",
    "evaluation": "not_executed_yet",
    "mixed_precision": "not_executed_yet",
    "mixed_precision_global_state": "not_executed_yet",
    "saveable_object_util": "not_executed_yet",
    "trace_saveable_util": "not_executed_yet",
    "save_util": "not_executed_yet",
    "checkpoint_view": "not_executed_yet",
    "tensor_callable": "not_executed_yet",
    "checkpoint": "not_executed_yet",
    "save_util_v1": "not_executed_yet",
    "checkpoint_options": "not_executed_yet",
    "async_checkpoint_helper": "not_executed_yet",
    "graph_view": "not_executed_yet",
    "restore": "not_executed_yet",
    "trackable_view": "not_executed_yet",
    "functional_saver": "not_executed_yet",
    "tf_logging": "not_executed_yet",
    "gfile": "not_executed_yet",
    "app": "not_executed_yet",
    "self_check": "not_executed_yet",
    "googletest": "not_executed_yet",
    "benchmark": "not_executed_yet",
    "flags": "not_executed_yet",
    "sysconfig": "not_executed_yet",
    "resource_loader": "not_executed_yet",
    "feature_column_v2_types": "not_executed_yet",
    "sequence_feature_column": "not_executed_yet",
    "freeze_graph": "not_executed_yet",
    "saved_model_aot_compile": "not_executed_yet",
    "optimize_for_inference": "not_executed_yet",
    "print_selective_registration_header": "not_executed_yet",
    "inspect_checkpoint": "not_executed_yet",
    "saved_model_cli": "not_executed_yet",
    "import_pb_to_tensorboard": "not_executed_yet",
    "selective_registration_header_lib": "not_executed_yet",
    "strip_unused": "not_executed_yet",
    "optimize_for_inference_lib": "not_executed_yet",
    "strip_unused_lib": "not_executed_yet",
    "generator": "not_executed_yet",
    "extractor": "not_executed_yet",
    "create_python_api": "not_executed_yet",
    "doc_srcs": "not_executed_yet",
    "status_pb2": "not_executed_yet",
    "gen_trt_ops": "not_executed_yet",
    "xla_ops": "not_executed_yet",
    "xla_ops_grad": "not_executed_yet",
    "hlo_pb2": "not_executed_yet",
    "gen_mlir_passthrough_op": "not_executed_yet",
    "exported_model_pb2": "not_executed_yet",
    "quantization_options_pb2": "not_executed_yet",
    "quantize_model": "not_executed_yet",
    "save_model": "not_executed_yet",
    "representative_dataset": "not_executed_yet",
    "calibration_algorithm": "not_executed_yet",
    "tf2xla_pb2": "not_executed_yet",
    "gen_xla_ops": "not_executed_yet",
    "op_hint": "not_executed_yet",
    "schema_util": "not_executed_yet",
    "tflite_keras_util": "not_executed_yet",
    "wrap_toco": "not_executed_yet",
    "lite": "not_executed_yet",
    "analyzer": "not_executed_yet",
    "tflite_convert": "not_executed_yet",
    "lite_constants": "not_executed_yet",
    "interpreter": "not_executed_yet",
    "convert_phase": "not_executed_yet",
    "convert_saved_model": "not_executed_yet",
    "metrics_wrapper": "not_executed_yet",
    "calibrator": "not_executed_yet",
    "authoring": "not_executed_yet",
    "audio_microfrontend_op": "not_executed_yet",
    "gen_audio_microfrontend_op": "not_executed_yet",
    "toco_flags_pb2": "not_executed_yet",
    "model_flags_pb2": "not_executed_yet",
    "toco_from_protos": "not_executed_yet",
    "gen_html": "not_executed_yet",
    "visualize": "not_executed_yet",
    "flatbuffer_utils": "not_executed_yet",
    "debugger": "not_executed_yet",
    "tf_rpc_service_pb2_grpc": "not_executed_yet",
    "tf_rpc_service_pb2": "not_executed_yet",
    "gen_rpc_ops": "not_executed_yet",
    "v2": "not_executed_yet",
    "accelerator_util": "not_executed_yet",
    "d_checkpoint": "not_executed_yet",
    "layout": "not_executed_yet",
    "numpy_util": "not_executed_yet",
    "mesh_util": "not_executed_yet",
    "gen_dtensor_ops": "not_executed_yet",
    "d_variable": "not_executed_yet",
    "save_restore": "not_executed_yet",
    "dtensor_device": "not_executed_yet",
    "test_backend_util": "not_executed_yet",
    "test_util_ops": "not_executed_yet",
    "multi_client_test_util": "not_executed_yet",
    "debug_service_pb2": "not_executed_yet",
    "profiler_options_pb2": "not_executed_yet",
    "tfprof_log_pb2": "not_executed_yet",
    "profile_pb2": "not_executed_yet",
    "tfprof_output_pb2": "not_executed_yet",
    "xplane_pb2": "not_executed_yet",
    "gen_check_preemption_op": "not_executed_yet",
    "op_performance_data_pb2": "not_executed_yet",
    "optimized_function_graph_pb2": "not_executed_yet",
    "graph_transfer_info_pb2": "not_executed_yet",
    "node_def_pb2": "not_executed_yet",
    "dataset_pb2": "not_executed_yet",
    "graph_pb2": "not_executed_yet",
    "log_memory_pb2": "not_executed_yet",
    "attr_value_pb2": "not_executed_yet",
    "step_stats_pb2": "not_executed_yet",
    "function_pb2": "not_executed_yet",
    "op_def_pb2": "not_executed_yet",
    "summary_pb2": "not_executed_yet",
    "resource_handle_pb2": "not_executed_yet",
    "kernel_def_pb2": "not_executed_yet",
    "cost_graph_pb2": "not_executed_yet",
    "dataset_options_pb2": "not_executed_yet",
    "tensor_description_pb2": "not_executed_yet",
    "tensor_pb2": "not_executed_yet",
    "api_def_pb2": "not_executed_yet",
    "custom_nest_trace_type": "not_executed_yet",
    "trace_type_builder": "not_executed_yet",
    "default_types": "not_executed_yet",
    "serialization_test_pb2": "not_executed_yet",
    "default_types_pb2": "not_executed_yet",
    "function_cache": "not_executed_yet",
    "type_dispatch": "not_executed_yet",
    "function_type": "not_executed_yet",
    "function_type_pb2": "not_executed_yet",
    "capture_container": "not_executed_yet",
    "restore_captures": "not_executed_yet",
    "saved_tensor_slice_pb2": "not_executed_yet",
    "test_log_pb2": "not_executed_yet",
    "event_pb2": "not_executed_yet",
    "example_pb2": "not_executed_yet",
    "example_parser_configuration_pb2": "not_executed_yet",
    "error_codes_pb2": "not_executed_yet",
    "config_pb2": "not_executed_yet",
    "named_tensor_pb2": "not_executed_yet",
    "saved_object_graph_pb2": "not_executed_yet",
    "rewriter_config_pb2": "not_executed_yet",
    "meta_graph_pb2": "not_executed_yet",
    "queue_runner_pb2": "not_executed_yet",
    "composite_tensor_variant_pb2": "not_executed_yet",
    "tensorflow_server_pb2": "not_executed_yet",
    "fingerprint_pb2": "not_executed_yet",
    "bfc_memory_map_pb2": "not_executed_yet",
    "snapshot_pb2": "not_executed_yet",
    "service_config_pb2": "not_executed_yet",
    "debug_event_pb2": "not_executed_yet",
    "remote_tensor_handle_pb2": "not_executed_yet",
    "rpc_options_pb2": "not_executed_yet",
    "struct_pb2": "not_executed_yet",
    "tensor_bundle_pb2": "not_executed_yet",
    "saved_model_pb2": "not_executed_yet",
    "optimization_parameters_pb2": "not_executed_yet",
    "tpu_embedding_configuration_pb2": "not_executed_yet",
    "compilation_result_pb2": "not_executed_yet",
    "all_renames_v2": "not_executed_yet",
    "tf_upgrade_v2": "not_executed_yet",
    "tf_upgrade_v2_main": "not_executed_yet",
    "tf_upgrade_v2_safety": "not_executed_yet",
    "module_deprecations_v2": "not_executed_yet",
    "public_api": "not_executed_yet",
    "test_module1": "not_executed_yet",
    "run_config": "not_executed_yet",
    "estimator": "not_executed_yet",
    "extenders": "not_executed_yet",
    "model_fn": "not_executed_yet",
    "early_stopping": "not_executed_yet",
    "estimator_export": "not_executed_yet",
    "gc": "not_executed_yet",
    "keras_lib": "not_executed_yet",
    "exporter": "not_executed_yet",
    "base_head": "not_executed_yet",
    "head_utils": "not_executed_yet",
    "multi_head": "not_executed_yet",
    "multi_label_head": "not_executed_yet",
    "regression_head": "not_executed_yet",
    "binary_class_head": "not_executed_yet",
    "sequential_head": "not_executed_yet",
    "multi_class_head": "not_executed_yet",
    "tpu_context": "not_executed_yet",
    "tpu_config": "not_executed_yet",
    "_tpu_estimator_embedding": "not_executed_yet",
    "iteration_count_estimator": "not_executed_yet",
    "error_handling": "not_executed_yet",
    "tpu_estimator": "not_executed_yet",
    "v1": "not_executed_yet",
    "fake_summary_writer": "not_executed_yet",
    "export_lib": "not_executed_yet",
    "export": "not_executed_yet",
    "feeding_functions": "not_executed_yet",
    "feeding_queue_runner": "not_executed_yet",
    "baseline": "not_executed_yet",
    "dnn_testing_utils": "not_executed_yet",
    "kmeans": "not_executed_yet",
    "parsing_utils": "not_executed_yet",
    "linear_testing_utils": "not_executed_yet",
    "saved_model_estimator": "not_executed_yet",
    "dnn": "not_executed_yet",
    "head": "not_executed_yet",
    "dnn_linear_combined": "not_executed_yet",
    "linear": "not_executed_yet",
    "feature_keys": "not_executed_yet",
    "estimators": "not_executed_yet",
    "model_utils": "not_executed_yet",
    "math_utils": "not_executed_yet",
    "ar_model": "not_executed_yet",
    "sharded_mutable_dense_hashtable": "not_executed_yet",
    "dnn_testing_utils_v1": "not_executed_yet",
    "linear_testing_utils_v1": "not_executed_yet",
    "checkpoint_converter": "not_executed_yet",
    "test_backends": "not_executed_yet",
    "tensorflow": "not_executed_yet",
    "text": "not_executed_yet",
    "image": "not_executed_yet",
    "sequence": "not_executed_yet",
    "keras_doctest": "not_executed_yet",
    "wide_deep": "not_executed_yet",
    "regression_metrics": "not_executed_yet",
    "confusion_metrics": "not_executed_yet",
    "hinge_metrics": "not_executed_yet",
    "py_metric": "not_executed_yet",
    "probabilistic_metrics": "not_executed_yet",
    "accuracy_metrics": "not_executed_yet",
    "iou_metrics": "not_executed_yet",
    "f_score_metrics": "not_executed_yet",
    "base_metric": "not_executed_yet",
    "adamw": "not_executed_yet",
    "lion": "not_executed_yet",
    "adafactor": "not_executed_yet",
    "sgd": "not_executed_yet",
    "image_utils": "not_executed_yet",
    "steps_per_execution_tuning": "not_executed_yet",
    "timed_threads": "not_executed_yet",
    "text_dataset": "not_executed_yet",
    "feature_space": "not_executed_yet",
    "image_dataset": "not_executed_yet",
    "kpl_test_utils": "not_executed_yet",
    "sidecar_evaluator": "not_executed_yet",
    "io_utils": "not_executed_yet",
    "dataset_utils": "not_executed_yet",
    "timeseries_dataset": "not_executed_yet",
    "audio_dataset": "not_executed_yet",
    "migration_utils": "not_executed_yet",
    "kernelized": "not_executed_yet",
    "text_vectorization": "not_executed_yet",
    "discretization": "not_executed_yet",
    "image_preprocessing": "not_executed_yet",
    "index_lookup": "not_executed_yet",
    "integer_lookup": "not_executed_yet",
    "preprocessing_test_utils": "not_executed_yet",
    "preprocessing_utils": "not_executed_yet",
    "preprocessing_stage": "not_executed_yet",
    "hashed_crossing": "not_executed_yet",
    "category_encoding": "not_executed_yet",
    "string_lookup": "not_executed_yet",
    "hashing": "not_executed_yet",
    "category_hash_varlen_benchmark": "not_executed_yet",
    "embedding_dense_benchmark": "not_executed_yet",
    "category_vocab_list_indicator_varlen_benchmark": "not_executed_yet",
    "bucketized_column_dense_benchmark": "not_executed_yet",
    "hashing_benchmark": "not_executed_yet",
    "index_lookup_adapt_benchmark": "not_executed_yet",
    "category_encoding_benchmark": "not_executed_yet",
    "embedding_varlen_benchmark": "not_executed_yet",
    "category_vocab_list_indicator_dense_benchmark": "not_executed_yet",
    "discretization_adapt_benchmark": "not_executed_yet",
    "category_vocab_file_varlen_benchmark": "not_executed_yet",
    "hashed_crossing_benchmark": "not_executed_yet",
    "index_lookup_forward_benchmark": "not_executed_yet",
    "category_vocab_list_varlen_benchmark": "not_executed_yet",
    "category_vocab_file_dense_benchmark": "not_executed_yet",
    "image_preproc_benchmark": "not_executed_yet",
    "normalization_adapt_benchmark": "not_executed_yet",
    "category_vocab_list_dense_benchmark": "not_executed_yet",
    "category_hash_dense_benchmark": "not_executed_yet",
    "feature_column_benchmark": "not_executed_yet",
    "weighted_embedding_varlen_benchmark": "not_executed_yet",
    "relu": "not_executed_yet",
    "thresholded_relu": "not_executed_yet",
    "leaky_relu": "not_executed_yet",
    "softmax": "not_executed_yet",
    "prelu": "not_executed_yet",
    "elu": "not_executed_yet",
    "concatenate": "not_executed_yet",
    "subtract": "not_executed_yet",
    "base_merge": "not_executed_yet",
    "dot": "not_executed_yet",
    "minimum": "not_executed_yet",
    "average": "not_executed_yet",
    "add": "not_executed_yet",
    "maximum": "not_executed_yet",
    "multiply": "not_executed_yet",
    "conv3d_transpose": "not_executed_yet",
    "separable_conv2d": "not_executed_yet",
    "depthwise_conv1d": "not_executed_yet",
    "conv2d": "not_executed_yet",
    "conv1d_transpose": "not_executed_yet",
    "conv1d": "not_executed_yet",
    "base_conv": "not_executed_yet",
    "depthwise_conv2d": "not_executed_yet",
    "separable_conv1d": "not_executed_yet",
    "conv2d_transpose": "not_executed_yet",
    "conv3d": "not_executed_yet",
    "base_depthwise_conv": "not_executed_yet",
    "base_separable_conv": "not_executed_yet",
    "base_dense_attention": "not_executed_yet",
    "multi_head_attention": "not_executed_yet",
    "attention": "not_executed_yet",
    "additive_attention": "not_executed_yet",
    "base_cudnn_rnn": "not_executed_yet",
    "cudnn_gru": "not_executed_yet",
    "rnn_utils": "not_executed_yet",
    "time_distributed": "not_executed_yet",
    "abstract_rnn_cell": "not_executed_yet",
    "legacy_cell_wrappers": "not_executed_yet",
    "base_conv_lstm": "not_executed_yet",
    "base_conv_rnn": "not_executed_yet",
    "base_wrapper": "not_executed_yet",
    "conv_lstm2d": "not_executed_yet",
    "lstm_v1": "not_executed_yet",
    "base_rnn": "not_executed_yet",
    "gru_lstm_utils": "not_executed_yet",
    "dropout_rnn_cell_mixin": "not_executed_yet",
    "conv_lstm3d": "not_executed_yet",
    "lstm": "not_executed_yet",
    "gru": "not_executed_yet",
    "conv_lstm1d": "not_executed_yet",
    "cell_wrappers": "not_executed_yet",
    "stacked_rnn_cells": "not_executed_yet",
    "legacy_cells": "not_executed_yet",
    "bidirectional": "not_executed_yet",
    "gru_v1": "not_executed_yet",
    "cudnn_lstm": "not_executed_yet",
    "simple_rnn": "not_executed_yet",
    "base_pooling1d": "not_executed_yet",
    "max_pooling3d": "not_executed_yet",
    "base_global_pooling1d": "not_executed_yet",
    "average_pooling1d": "not_executed_yet",
    "base_global_pooling2d": "not_executed_yet",
    "max_pooling1d": "not_executed_yet",
    "global_average_pooling1d": "not_executed_yet",
    "global_max_pooling2d": "not_executed_yet",
    "base_pooling3d": "not_executed_yet",
    "global_average_pooling3d": "not_executed_yet",
    "global_max_pooling3d": "not_executed_yet",
    "base_global_pooling3d": "not_executed_yet",
    "average_pooling2d": "not_executed_yet",
    "base_pooling2d": "not_executed_yet",
    "average_pooling3d": "not_executed_yet",
    "global_max_pooling1d": "not_executed_yet",
    "global_average_pooling2d": "not_executed_yet",
    "max_pooling2d": "not_executed_yet",
    "locally_connected1d": "not_executed_yet",
    "locally_connected_utils": "not_executed_yet",
    "locally_connected2d": "not_executed_yet",
    "lambda_layer": "not_executed_yet",
    "tf_op_layer": "not_executed_yet",
    "identity": "not_executed_yet",
    "dense": "not_executed_yet",
    "einsum_dense": "not_executed_yet",
    "masking": "not_executed_yet",
    "embedding": "not_executed_yet",
    "activation": "not_executed_yet",
    "alpha_dropout": "not_executed_yet",
    "spatial_dropout1d": "not_executed_yet",
    "spatial_dropout2d": "not_executed_yet",
    "spatial_dropout3d": "not_executed_yet",
    "gaussian_dropout": "not_executed_yet",
    "dropout": "not_executed_yet",
    "gaussian_noise": "not_executed_yet",
    "activity_regularization": "not_executed_yet",
    "zero_padding3d": "not_executed_yet",
    "up_sampling2d": "not_executed_yet",
    "up_sampling3d": "not_executed_yet",
    "cropping1d": "not_executed_yet",
    "up_sampling1d": "not_executed_yet",
    "repeat_vector": "not_executed_yet",
    "zero_padding2d": "not_executed_yet",
    "flatten": "not_executed_yet",
    "cropping2d": "not_executed_yet",
    "reshape": "not_executed_yet",
    "cropping3d": "not_executed_yet",
    "permute": "not_executed_yet",
    "zero_padding1d": "not_executed_yet",
    "batch_normalization": "not_executed_yet",
    "group_normalization": "not_executed_yet",
    "spectral_normalization": "not_executed_yet",
    "unit_normalization": "not_executed_yet",
    "batch_normalization_v1": "not_executed_yet",
    "layer_normalization": "not_executed_yet",
    "test_utils": "not_executed_yet",
    "initializers": "not_executed_yet",
    "sharpness_aware_minimization": "not_executed_yet",
    "cloning": "not_executed_yet",
    "distribution_util": "not_executed_yet",
    "test_example": "not_executed_yet",
    "optimizer_combinations": "not_executed_yet",
    "multi_worker_testing_utils": "not_executed_yet",
    "tpu_strategy_test_utils": "not_executed_yet",
    "dataset_creator_model_fit_test_base": "not_executed_yet",
    "simple_models": "not_executed_yet",
    "keras_correctness_test_base": "not_executed_yet",
    "model_combinations": "not_executed_yet",
    "saved_model_test_base": "not_executed_yet",
    "convnext": "not_executed_yet",
    "mobilenet_v3": "not_executed_yet",
    "vgg16": "not_executed_yet",
    "efficientnet_v2": "not_executed_yet",
    "densenet": "not_executed_yet",
    "resnet_v2": "not_executed_yet",
    "inception_v3": "not_executed_yet",
    "imagenet_utils": "not_executed_yet",
    "regnet": "not_executed_yet",
    "mobilenet_v2": "not_executed_yet",
    "vgg19": "not_executed_yet",
    "efficientnet": "not_executed_yet",
    "nasnet": "not_executed_yet",
    "inception_resnet_v2": "not_executed_yet",
    "xception": "not_executed_yet",
    "resnet": "not_executed_yet",
    "mobilenet": "not_executed_yet",
    "resnet_rs": "not_executed_yet",
    "functional_utils": "not_executed_yet",
    "fashion_mnist": "not_executed_yet",
    "reuters": "not_executed_yet",
    "cifar100": "not_executed_yet",
    "cifar10": "not_executed_yet",
    "boston_housing": "not_executed_yet",
    "mnist": "not_executed_yet",
    "imdb": "not_executed_yet",
    "lazy_variable": "not_executed_yet",
    "integration_test_utils": "not_executed_yet",
    "layout_map": "not_executed_yet",
    "dense_features_v2": "not_executed_yet",
    "dense_features": "not_executed_yet",
    "base_feature_layer": "not_executed_yet",
    "saving_api": "not_executed_yet",
    "saving_lib": "not_executed_yet",
    "serialization_lib": "not_executed_yet",
    "pickle_utils": "not_executed_yet",
    "object_registration": "not_executed_yet",
    "create_test_saved_model": "not_executed_yet",
    "load_context": "not_executed_yet",
    "event_file_loader": "not_executed_yet",
    "op_evaluator": "not_executed_yet",
    "encoder": "not_executed_yet",
    "debug_data_multiplexer": "not_executed_yet",
    "summary_v2": "not_executed_yet",
    "_keras": "not_executed_yet",
    "execution": "not_executed_yet"
}